[
  {
    "id": 0,
    "category": "1.ATPL_OXFORD",
    "subject": "9.METEOROLOGY",
    "chapter": "1.1.1.The Atmosphere",
    "version": 0,
    "testQuestionMarking": 0,
    "duration": 3600,
    "questions": [
      {
        "id": 0,
        "questionNumber": "1",
        "question": "How does the height of the tropopause normally vary with latitude in the Northern Hemisphere?",
        "mark": 0,
        "isActive": true,
        "answerType": 0,
        "supplements": [],
        "options": [
          {
            "id": 0,
            "tenantId": "A",
            "content": "It decreases from south to north",
            "isTrue": true
          },
          {
            "id": 0,
            "tenantId": "B",
            "content": "It increases from south to north",
            "isTrue": false
          },
          {
            "id": 0,
            "tenantId": "C",
            "content": "It remains constant from north to south",
            "isTrue": false
          },
          {
            "id": 0,
            "tenantId": "D",
            "content": "It remains constant throughout the year",
            "isTrue": false
          }
        ]
      },
      {
        "id": 0,
        "questionNumber": "2",
        "question": "What, approximately, is the average height of the tropopause over the Equator?",
        "mark": 0,
        "isActive": true,
        "answerType": 0,
        "supplements": [],
        "options": [
          {
            "id": 0,
            "tenantId": "A",
            "content": "8 km",
            "isTrue": false
          },
          {
            "id": 0,
            "tenantId": "B",
            "content": "16 km",
            "isTrue": true
          },
          {
            "id": 0,
            "tenantId": "C",
            "content": "11 km",
            "isTrue": false
          },
          {
            "id": 0,
            "tenantId": "D",
            "content": "50 km",
            "isTrue": false
          }
        ]
      },
      {
        "id": 0,
        "questionNumber": "3",
        "question": "In the International Standard Atmosphere the decrease in temperature with height below 11 km is:",
        "mark": 0,
        "isActive": true,
        "answerType": 0,
        "supplements": [],
        "options": [
          {
            "id": 0,
            "tenantId": "A",
            "content": "0.5&#8451;/100 m",
            "isTrue": false
          },
          {
            "id": 0,
            "tenantId": "B",
            "content": "0.6&#8451;/100 m",
            "isTrue": false
          },
          {
            "id": 0,
            "tenantId": "C",
            "content": "0.65&#8451;/100 m",
            "isTrue": true
          },
          {
            "id": 0,
            "tenantId": "D",
            "content": "1&#8451;/100 m",
            "isTrue": false
          }
        ]
      },
      {
        "id": 0,
        "questionNumber": "4",
        "question": "The 200 hPa pressure altitude level can vary in height. In temperate regions which of the following average heights is applicable?",
        "mark": 0,
        "isActive": true,
        "answerType": 0,
        "supplements": [],
        "options": [
          {
            "id": 0,
            "tenantId": "A",
            "content": "FL390",
            "isTrue": true
          },
          {
            "id": 0,
            "tenantId": "B",
            "content": "FL300",
            "isTrue": false
          },
          {
            "id": 0,
            "tenantId": "C",
            "content": "FL100",
            "isTrue": false
          },
          {
            "id": 0,
            "tenantId": "D",
            "content": "FL50",
            "isTrue": false
          }
        ]
      },
      {
        "id": 0,
        "questionNumber": "5",
        "question": "The temperature at FL110 is -12&#8451;. What will the temperature be at FL140 if the ICAO standard lapse rate is applied?",
        "mark": 0,
        "isActive": true,
        "answerType": 0,
        "supplements": [],
        "options": [
          {
            "id": 0,
            "tenantId": "A",
            "content": "-6&#8451;",
            "isTrue": false
          },
          {
            "id": 0,
            "tenantId": "B",
            "content": "-18&#8451;",
            "isTrue": true
          },
          {
            "id": 0,
            "tenantId": "C",
            "content": "-9&#8451;",
            "isTrue": false
          },
          {
            "id": 0,
            "tenantId": "D",
            "content": "-15&#8451;",
            "isTrue": false
          }
        ]
      },
      {
        "id": 0,
        "questionNumber": "6",
        "question": "<p>At a certain position the temperature on the 300 hPa chart is -54&#8451;, and according to the significant weather chart the tropopause is at FL330.</p><p>What is the most likely temperature at FL350?</p>",
        "mark": 0,
        "isActive": true,
        "answerType": 0,
        "supplements": [],
        "options": [
          {
            "id": 0,
            "tenantId": "A",
            "content": "-48&#8451;",
            "isTrue": false
          },
          {
            "id": 0,
            "tenantId": "B",
            "content": "-60&#8451;",
            "isTrue": true
          },
          {
            "id": 0,
            "tenantId": "C",
            "content": "-56.5&#8451;",
            "isTrue": false
          },
          {
            "id": 0,
            "tenantId": "D",
            "content": "-64&#8451;",
            "isTrue": false
          }
        ]
      },
      {
        "id": 0,
        "questionNumber": "7",
        "question": "What is the boundary between the troposphere and the stratosphere called?",
        "mark": 0,
        "isActive": true,
        "answerType": 0,
        "supplements": [],
        "options": [
          {
            "id": 0,
            "tenantId": "A",
            "content": "Ionosphere",
            "isTrue": false
          },
          {
            "id": 0,
            "tenantId": "B",
            "content": "Stratosphere",
            "isTrue": false
          },
          {
            "id": 0,
            "tenantId": "C",
            "content": "Atmosphere",
            "isTrue": false
          },
          {
            "id": 0,
            "tenantId": "D",
            "content": "Tropopause",
            "isTrue": true
          }
        ]
      },
      {
        "id": 0,
        "questionNumber": "8",
        "question": "Which constant pressure altitude chart is standard for 4781 ft pressure level (FL50)?",
        "mark": 0,
        "isActive": true,
        "answerType": 0,
        "supplements": [],
        "options": [
          {
            "id": 0,
            "tenantId": "A",
            "content": "500 hPa",
            "isTrue": false
          },
          {
            "id": 0,
            "tenantId": "B",
            "content": "300 hPa",
            "isTrue": false
          },
          {
            "id": 0,
            "tenantId": "C",
            "content": "850 hPa",
            "isTrue": true
          },
          {
            "id": 0,
            "tenantId": "D",
            "content": "700 hPa",
            "isTrue": false
          }
        ]
      },
      {
        "id": 0,
        "questionNumber": "9",
        "question": "<p>An outside air temperature of -30&#8451; is measured whilst cruising at FL200.</p><p>What is the temperature deviation from the ISA at this level?</p>",
        "mark": 0,
        "isActive": true,
        "answerType": 0,
        "supplements": [],
        "options": [
          {
            "id": 0,
            "tenantId": "A",
            "content": "5&#8451; colder than ISA",
            "isTrue": true
          },
          {
            "id": 0,
            "tenantId": "B",
            "content": "5&#8451; warmer than ISA",
            "isTrue": false
          },
          {
            "id": 0,
            "tenantId": "C",
            "content": "10&#8451; colder than ISA",
            "isTrue": false
          },
          {
            "id": 0,
            "tenantId": "D",
            "content": "10&#8451; warmer than ISA",
            "isTrue": false
          }
        ]
      },
      {
        "id": 0,
        "questionNumber": "10",
        "question": "What is the most likely temperature at the tropical tropopause?",
        "mark": 0,
        "isActive": true,
        "answerType": 0,
        "supplements": [],
        "options": [
          {
            "id": 0,
            "tenantId": "A",
            "content": "-56.5&#8451;",
            "isTrue": false
          },
          {
            "id": 0,
            "tenantId": "B",
            "content": "-75&#8451;",
            "isTrue": true
          },
          {
            "id": 0,
            "tenantId": "C",
            "content": "-40&#8451;",
            "isTrue": false
          },
          {
            "id": 0,
            "tenantId": "D",
            "content": "-25&#8451;",
            "isTrue": false
          }
        ]
      },
      {
        "id": 0,
        "questionNumber": "11",
        "question": "Which one of the following statements applies to the tropopause?",
        "mark": 0,
        "isActive": true,
        "answerType": 0,
        "supplements": [],
        "options": [
          {
            "id": 0,
            "tenantId": "A",
            "content": "It is, by definition, an isothermal layer",
            "isTrue": false
          },
          {
            "id": 0,
            "tenantId": "B",
            "content": "It indicates a strong temperature lapse rate",
            "isTrue": false
          },
          {
            "id": 0,
            "tenantId": "C",
            "content": "It is, by definition a temperature inversion",
            "isTrue": false
          },
          {
            "id": 0,
            "tenantId": "D",
            "content": "It separates the troposphere from the stratosphere",
            "isTrue": true
          }
        ]
      },
      {
        "id": 0,
        "questionNumber": "12",
        "question": "In the lower part of the stratosphere the temperature:",
        "mark": 0,
        "isActive": true,
        "answerType": 0,
        "supplements": [],
        "options": [
          {
            "id": 0,
            "tenantId": "A",
            "content": "is almost constant",
            "isTrue": true
          },
          {
            "id": 0,
            "tenantId": "B",
            "content": "decreases with altitude",
            "isTrue": false
          },
          {
            "id": 0,
            "tenantId": "C",
            "content": "increases with altitude",
            "isTrue": false
          },
          {
            "id": 0,
            "tenantId": "D",
            "content": "increases at first and decreases afterwards",
            "isTrue": false
          }
        ]
      },
      {
        "id": 0,
        "questionNumber": "13",
        "question": "What is the approximate composition of the dry air by volume in the troposphere?",
        "mark": 0,
        "isActive": true,
        "answerType": 0,
        "supplements": [],
        "options": [
          {
            "id": 0,
            "tenantId": "A",
            "content": "10&#37; oxygen, 89&#37; nitrogen and the rest other gases",
            "isTrue": false
          },
          {
            "id": 0,
            "tenantId": "B",
            "content": "88&#37; oxygen, 9&#37; nitrogen and the rest other gases",
            "isTrue": false
          },
          {
            "id": 0,
            "tenantId": "C",
            "content": "50&#37; oxygen, 40&#37; nitrogen and the rest other gases",
            "isTrue": false
          },
          {
            "id": 0,
            "tenantId": "D",
            "content": "21&#37; oxygen, 78&#37; nitrogen and the rest other gases",
            "isTrue": true
          }
        ]
      },
      {
        "id": 0,
        "questionNumber": "14",
        "question": "How does temperature vary with increasing altitude in the ICAO standard atmosphere below the tropopause?",
        "mark": 0,
        "isActive": true,
        "answerType": 0,
        "supplements": [],
        "options": [
          {
            "id": 0,
            "tenantId": "A",
            "content": "Remains constant",
            "isTrue": false
          },
          {
            "id": 0,
            "tenantId": "B",
            "content": "Decreases",
            "isTrue": true
          },
          {
            "id": 0,
            "tenantId": "C",
            "content": "Increases",
            "isTrue": false
          },
          {
            "id": 0,
            "tenantId": "D",
            "content": "At first it increases and higher up it decreases",
            "isTrue": false
          }
        ]
      },
      {
        "id": 0,
        "questionNumber": "15",
        "question": "How would you characterize an air temperature of -15&#8451; at the 700 hPa level over western Europe?",
        "mark": 0,
        "isActive": true,
        "answerType": 0,
        "supplements": [],
        "options": [
          {
            "id": 0,
            "tenantId": "A",
            "content": "Within &#177;5&#8451; of ISA",
            "isTrue": false
          },
          {
            "id": 0,
            "tenantId": "B",
            "content": "20&#8451; below standard",
            "isTrue": false
          },
          {
            "id": 0,
            "tenantId": "C",
            "content": "Low",
            "isTrue": true
          },
          {
            "id": 0,
            "tenantId": "D",
            "content": "High",
            "isTrue": false
          }
        ]
      },
      {
        "id": 0,
        "questionNumber": "16",
        "question": "If you are flying at FL300 in an air mass that is 15&#8451; warmer than a standard atmosphere what is the outside temperature likely to be?",
        "mark": 0,
        "isActive": true,
        "answerType": 0,
        "supplements": [],
        "options": [
          {
            "id": 0,
            "tenantId": "A",
            "content": "-15&#8451;",
            "isTrue": false
          },
          {
            "id": 0,
            "tenantId": "B",
            "content": "-30&#8451;",
            "isTrue": true
          },
          {
            "id": 0,
            "tenantId": "C",
            "content": "-45&#8451;",
            "isTrue": false
          },
          {
            "id": 0,
            "tenantId": "D",
            "content": "-60&#8451;",
            "isTrue": false
          }
        ]
      },
      {
        "id": 0,
        "questionNumber": "17",
        "question": "If you are flying at FL140 and the outside temperature is -8&#8451; at what altitude will the freezing level be?",
        "mark": 0,
        "isActive": true,
        "answerType": 0,
        "supplements": [],
        "options": [
          {
            "id": 0,
            "tenantId": "A",
            "content": "FL75",
            "isTrue": false
          },
          {
            "id": 0,
            "tenantId": "B",
            "content": "FL100",
            "isTrue": true
          },
          {
            "id": 0,
            "tenantId": "C",
            "content": "FL130",
            "isTrue": false
          },
          {
            "id": 0,
            "tenantId": "D",
            "content": "FL180",
            "isTrue": false
          }
        ]
      },
      {
        "id": 0,
        "questionNumber": "18",
        "question": "What is the most important constituent in the atmosphere from a weather standpoint?",
        "mark": 0,
        "isActive": true,
        "answerType": 0,
        "supplements": [],
        "options": [
          {
            "id": 0,
            "tenantId": "A",
            "content": "Carbon dioxide",
            "isTrue": false
          },
          {
            "id": 0,
            "tenantId": "B",
            "content": "Oxygen",
            "isTrue": false
          },
          {
            "id": 0,
            "tenantId": "C",
            "content": "Water vapour",
            "isTrue": true
          },
          {
            "id": 0,
            "tenantId": "D",
            "content": "Methane",
            "isTrue": false
          }
        ]
      },
      {
        "id": 0,
        "questionNumber": "19",
        "question": "The average height of the tropopause at a latitude of 50&#8451; is about:",
        "mark": 0,
        "isActive": true,
        "answerType": 0,
        "supplements": [],
        "options": [
          {
            "id": 0,
            "tenantId": "A",
            "content": "8 km",
            "isTrue": false
          },
          {
            "id": 0,
            "tenantId": "B",
            "content": "11 km",
            "isTrue": true
          },
          {
            "id": 0,
            "tenantId": "C",
            "content": "14 km",
            "isTrue": false
          },
          {
            "id": 0,
            "tenantId": "D",
            "content": "16 km",
            "isTrue": false
          }
        ]
      },
      {
        "id": 0,
        "questionNumber": "20",
        "question": "Between mean sea level and a height of 20 km the lowest temperature in the international standard atmosphere (ISA) is:",
        "mark": 0,
        "isActive": true,
        "answerType": 0,
        "supplements": [],
        "options": [
          {
            "id": 0,
            "tenantId": "A",
            "content": "-273&#8451;",
            "isTrue": false
          },
          {
            "id": 0,
            "tenantId": "B",
            "content": "-44.7&#8451;",
            "isTrue": false
          },
          {
            "id": 0,
            "tenantId": "C",
            "content": "-56.5&#8451;",
            "isTrue": true
          },
          {
            "id": 0,
            "tenantId": "D",
            "content": "-100&#8451;",
            "isTrue": false
          }
        ]
      },
      {
        "id": 0,
        "questionNumber": "21",
        "question": "The international standard atmosphere (ISA) assumes that the temperature will reduce at a rate of:",
        "mark": 0,
        "isActive": true,
        "answerType": 0,
        "supplements": [],
        "options": [
          {
            "id": 0,
            "tenantId": "A",
            "content": "1.98&#8451; per 1000 feet up to 36 090 feet after which it remains constant to 65 617 feet",
            "isTrue": true
          },
          {
            "id": 0,
            "tenantId": "B",
            "content": "1.98&#8451; per 1000 feet up to 36 090 feet and then will rise at 0.3&#8451; per 1000 feet up to 65 617 feet when it will remain constant",
            "isTrue": false
          },
          {
            "id": 0,
            "tenantId": "C",
            "content": "2&#8451; per 1000 feet up to 65 617 feet after which it will remain constant to 104 987 feet",
            "isTrue": false
          },
          {
            "id": 0,
            "tenantId": "D",
            "content": "2&#8451; per 1000 feet up to 36 090 feet and will then increase at 0.3&#8451; per 1000 feet up to 65 617 feet",
            "isTrue": false
          }
        ]
      },
      {
        "id": 0,
        "questionNumber": "22",
        "question": "In the mid-latitudes the stratosphere extends on average from:",
        "mark": 0,
        "isActive": true,
        "answerType": 0,
        "supplements": [],
        "options": [
          {
            "id": 0,
            "tenantId": "A",
            "content": "0 to 11 km",
            "isTrue": false
          },
          {
            "id": 0,
            "tenantId": "B",
            "content": "11 to 50 km",
            "isTrue": true
          },
          {
            "id": 0,
            "tenantId": "C",
            "content": "50 to 85 km",
            "isTrue": false
          },
          {
            "id": 0,
            "tenantId": "D",
            "content": "11 to 20 km",
            "isTrue": false
          }
        ]
      },
      {
        "id": 0,
        "questionNumber": "23",
        "question": "In relation to the total weight of the atmosphere, the weight of the atmosphere between mean sea level and a height of 5500 m is approximately:",
        "mark": 0,
        "isActive": true,
        "answerType": 0,
        "supplements": [],
        "options": [
          {
            "id": 0,
            "tenantId": "A",
            "content": "1&#37;",
            "isTrue": false
          },
          {
            "id": 0,
            "tenantId": "B",
            "content": "25&#37;",
            "isTrue": false
          },
          {
            "id": 0,
            "tenantId": "C",
            "content": "50&#37;",
            "isTrue": true
          },
          {
            "id": 0,
            "tenantId": "D",
            "content": "99&#37;",
            "isTrue": false
          }
        ]
      },
      {
        "id": 0,
        "questionNumber": "24",
        "question": "<p>A temperature of +15&#8451; is recorded at an altitude of 500 metres above mean sea level. If the vertical temperature gradient is that of a standard atmosphere,</p><p>what will be the temperature at the summit of a mountain 2500 metres above mean sea level?</p>",
        "mark": 0,
        "isActive": true,
        "answerType": 0,
        "supplements": [],
        "options": [
          {
            "id": 0,
            "tenantId": "A",
            "content": "0&#8451;",
            "isTrue": false
          },
          {
            "id": 0,
            "tenantId": "B",
            "content": "+2&#8451;",
            "isTrue": true
          },
          {
            "id": 0,
            "tenantId": "C",
            "content": "+4&#8451;",
            "isTrue": false
          },
          {
            "id": 0,
            "tenantId": "D",
            "content": "-2&#8451;",
            "isTrue": false
          }
        ]
      }
    ]
  }
]